vspacker/__init__.py
vspacker/downloader.py
vspacker/io.py
vspacker/manifest.json
vspacker/package_builder.py
vspacker/vs_project.py
VSPacker-0.0.7.dist-info/LICENSE
VSPacker-0.0.7.dist-info/METADATA
VSPacker-0.0.7.dist-info/WHEEL
VSPacker-0.0.7.dist-info/top_level.txt
VSPacker-0.0.7.dist-info/RECORD
