Metadata-Version: 2.1
Name: VSPacker
Version: 0.0.7
Summary: A simple library for automating ziping binary files for distribution in Visual Studio
Home-page: https://github.com/sean1832/vspacker.git
Author: Zeke Zhang
Classifier: Development Status :: 1 - Planning
Classifier: Programming Language :: Python :: 3.7
Classifier: Topic :: Utilities
Requires-Python: >=3.7
License-File: LICENSE
